LICENSE.txt
README.md
pyproject.toml
setup.cfg
setup.py
custom_toolbar_button/__init__.py
custom_toolbar_button/common.py
custom_toolbar_button/tool_qt.py
custom_toolbar_button/tool_tk.py
custom_toolbar_button.egg-info/PKG-INFO
custom_toolbar_button.egg-info/SOURCES.txt
custom_toolbar_button.egg-info/dependency_links.txt
custom_toolbar_button.egg-info/requires.txt
custom_toolbar_button.egg-info/top_level.txt
custom_toolbar_button/images/bshift.png
custom_toolbar_button/images/fshift.png