Metadata-Version: 2.1
Name: custom-toolbar-button
Version: 0.1.1
Summary: # Custom-toolbar-button
Home-page: https://github.com/jmishra01/Custom-button-in-Matplotlib-toolbar
Author: Jitendra Mishra
Author-email: jitendra29mishra@gmail.com
License: MIT
Keywords: matplotlib,toolbar,tkinter,qt
Platform: UNKNOWN
Classifier: Intended Audience :: Developers
Classifier: Topic :: Software Development :: Build Tools
Classifier: License :: OSI Approved :: MIT License
Classifier: Programming Language :: Python :: 3
Classifier: Programming Language :: Python :: 3.5
Classifier: Programming Language :: Python :: 3.6
Classifier: Programming Language :: Python :: 3.7
Classifier: Programming Language :: Python :: 3.8
Classifier: Programming Language :: Python :: 3.9
Classifier: Programming Language :: Python :: 3.10
License-File: LICENSE.txt
